{
  "protocol_version" : "0.0.5",
  "configuration" : {
    "version" : "(6.6.0.155) (2019-08/296a9afdb24)",
    "tlc" : "normal",
    "sigsgev" : "altstack",
    "notifications" : "kqueue",
    "architecture" : "amd64",
    "disabled_features" : "none",
    "smallconfig" : "disabled",
    "bigarrays" : "disabled",
    "softdebug" : "enabled",
    "interpreter" : "enabled",
    "llvm_support" : "0",
    "suspend" : "hybrid"
  },
  "memory" : {
    "Resident Size" : "26513408",
    "Virtual Size" : "4555395072",
    "minor_gc_time" : "0",
    "major_gc_time" : "0",
    "minor_gc_count" : "0",
    "major_gc_count" : "0",
    "major_gc_time_concurrent" : "0"
 },
  "threads" : [
 {
    "is_managed" : false,
    "offset_free_hash" : "0x0",
    "offset_rich_hash" : "0x0",
    "crashed" : false,
    "native_thread_id" : "0x700009e8d000",
    "thread_info_addr" : "0x7fdeb7808a00",
    "thread_name" : "Finalizer",
    "ctx" : {
      "IP" : "0x7fff6c111e36",
      "SP" : "0x700009e8ce48",
      "BP" : "0x700009e8cef0"
  },
    "unmanaged_frames" : [
  {
      "is_managed" : "false",
      "native_address" : "0x109a82156",
      "native_offset" : "0x00000"
   }
,
  {
      "is_managed" : "false",
      "native_address" : "0x109c28775",
      "native_offset" : "0x00000"
   }
,
  {
      "is_managed" : "false",
      "native_address" : "0x109c284a7",
      "native_offset" : "0x00000"
   }
,
  {
      "is_managed" : "false",
      "native_address" : "0x109aecf3c",
      "native_offset" : "0x00000"
   }
,
  {
      "is_managed" : "false",
      "native_address" : "0x7fff6c1c95fd",
      "native_offset" : "0x00000"
   }
,
  {
      "is_managed" : "false",
      "native_address" : "0x7fff92ae9388",
      "native_offset" : "0x00000"
   }
,
  {
      "is_managed" : "false",
      "native_address" : "0x109c29373",
      "native_offset" : "0x00000"
   }
,
  {
      "is_managed" : "false",
      "native_address" : "0x7fff6c1d5109",
      "native_offset" : "0x00000"
   }
,
  {
      "is_managed" : "false",
      "native_address" : "0x7fff6c1d0b8b",
      "native_offset" : "0x00000"
   }

  ]
 },
 {
    "is_managed" : false,
    "offset_free_hash" : "0x0",
    "offset_rich_hash" : "0x0",
    "crashed" : false,
    "native_thread_id" : "0x1136fedc0",
    "thread_info_addr" : "0x7fdeb7011000",
    "thread_name" : "tid_307",
    "ctx" : {
      "IP" : "0x7fff6c114882",
      "SP" : "0x7ffee6230d08",
      "BP" : "0x7ffee6230da0"
  },
    "unmanaged_frames" : [
  {
      "is_managed" : "false",
      "native_address" : "0x109a82156",
      "native_offset" : "0x00000"
   }
,
  {
      "is_managed" : "false",
      "native_address" : "0x109c28775",
      "native_offset" : "0x00000"
   }
,
  {
      "is_managed" : "false",
      "native_address" : "0x109c284a7",
      "native_offset" : "0x00000"
   }
,
  {
      "is_managed" : "false",
      "native_address" : "0x109aecf3c",
      "native_offset" : "0x00000"
   }
,
  {
      "is_managed" : "false",
      "native_address" : "0x7fff6c1c95fd",
      "native_offset" : "0x00000"
   }
,
  {
      "is_managed" : "false",
      "native_address" : "0x7ffee62309f8",
      "native_offset" : "0x00000"
   }
,
  {
      "is_managed" : "false",
      "native_address" : "0x109cd27c0",
      "native_offset" : "0x00000"
   }
,
  {
      "is_managed" : "false",
      "native_address" : "0x109ced2e1",
      "native_offset" : "0x00000"
   }
,
  {
      "is_managed" : "false",
      "native_address" : "0x109c25774",
      "native_offset" : "0x00000"
   }
,
  {
      "is_managed" : "false",
      "native_address" : "0x109c2558a",
      "native_offset" : "0x00000"
   }
,
  {
      "is_managed" : "false",
      "native_address" : "0x109a476c2",
      "native_offset" : "0x00000"
   }
,
  {
      "is_managed" : "false",
      "native_address" : "0x1099d1848",
      "native_offset" : "0x00000"
   }
,
  {
      "is_managed" : "false",
      "native_address" : "0x7fff6bfd0cc9",
      "native_offset" : "0x00000"
   }
,
  {
      "is_managed" : "false",
      "native_address" : "0x5",
      "native_offset" : "0x00000"
   }

  ]
 },
 {
    "is_managed" : true,
    "offset_free_hash" : "0xdd6a26835",
    "offset_rich_hash" : "0xdd6a26ae9",
    "crashed" : true,
    "native_thread_id" : "0x70000a59c000",
    "thread_info_addr" : "0x7fdeb7c5c400",
    "thread_name" : "Thread Pool Worker",
    "ctx" : {
      "IP" : "0x7fff6c11833a",
      "SP" : "0x70000a59a5e8",
      "BP" : "0x70000a59a610"
  },
    "managed_frames" : [
  {
      "is_managed" : "false",
      "native_address" : "unregistered"
   }
,
  {
      "is_managed" : "true",
      "guid" : "7D0BC631-CADD-4A07-BF74-717847E90CFA",
      "token" : "0x00000",
      "native_offset" : "0x0",
      "filename" : "mscorlib.dll",
      "sizeofimage" : "0x472000",
      "timestamp" : "0xec216ac8",
      "il_offset" : "0x0000c"
   }
,
  {
      "is_managed" : "true",
      "guid" : "7D0BC631-CADD-4A07-BF74-717847E90CFA",
      "token" : "0x6001f80",
      "native_offset" : "0x0",
      "filename" : "mscorlib.dll",
      "sizeofimage" : "0x472000",
      "timestamp" : "0xec216ac8",
      "il_offset" : "0x0001a"
   }
,
  {
      "is_managed" : "true",
      "guid" : "7D0BC631-CADD-4A07-BF74-717847E90CFA",
      "token" : "0x6001f27",
      "native_offset" : "0x0",
      "filename" : "mscorlib.dll",
      "sizeofimage" : "0x472000",
      "timestamp" : "0xec216ac8",
      "il_offset" : "0x00028"
   }
,
  {
      "is_managed" : "true",
      "guid" : "7D0BC631-CADD-4A07-BF74-717847E90CFA",
      "token" : "0x6001f25",
      "native_offset" : "0x0",
      "filename" : "mscorlib.dll",
      "sizeofimage" : "0x472000",
      "timestamp" : "0xec216ac8",
      "il_offset" : "0x00002"
   }
,
  {
      "is_managed" : "true",
      "guid" : "D5E8B245-CDEC-4B5A-9770-76E31BB9BD7E",
      "token" : "0x6000084",
      "native_offset" : "0x0",
      "filename" : "MonoDevelop.MSBuildBuilder.exe",
      "sizeofimage" : "0x14000",
      "timestamp" : "0x88f6a782",
      "il_offset" : "0x000ae"
   }
,
  {
      "is_managed" : "true",
      "guid" : "D5E8B245-CDEC-4B5A-9770-76E31BB9BD7E",
      "token" : "0x6000083",
      "native_offset" : "0x0",
      "filename" : "MonoDevelop.MSBuildBuilder.exe",
      "sizeofimage" : "0x14000",
      "timestamp" : "0x88f6a782",
      "il_offset" : "0x00001"
   }
,
  {
      "is_managed" : "true",
      "guid" : "D5E8B245-CDEC-4B5A-9770-76E31BB9BD7E",
      "token" : "0x600006a",
      "native_offset" : "0x0",
      "filename" : "MonoDevelop.MSBuildBuilder.exe",
      "sizeofimage" : "0x14000",
      "timestamp" : "0x88f6a782",
      "il_offset" : "0x00048"
   }
,
  {
      "is_managed" : "true",
      "guid" : "D5E8B245-CDEC-4B5A-9770-76E31BB9BD7E",
      "token" : "0x60000a1",
      "native_offset" : "0x0",
      "filename" : "MonoDevelop.MSBuildBuilder.exe",
      "sizeofimage" : "0x14000",
      "timestamp" : "0x88f6a782",
      "il_offset" : "0x00001"
   }
,
  {
      "is_managed" : "true",
      "guid" : "D5E8B245-CDEC-4B5A-9770-76E31BB9BD7E",
      "token" : "0x6000067",
      "native_offset" : "0x0",
      "filename" : "MonoDevelop.MSBuildBuilder.exe",
      "sizeofimage" : "0x14000",
      "timestamp" : "0x88f6a782",
      "il_offset" : "0x00001"
   }
,
  {
      "is_managed" : "true",
      "guid" : "D5E8B245-CDEC-4B5A-9770-76E31BB9BD7E",
      "token" : "0x6000075",
      "native_offset" : "0x0",
      "filename" : "MonoDevelop.MSBuildBuilder.exe",
      "sizeofimage" : "0x14000",
      "timestamp" : "0x88f6a782",
      "il_offset" : "0x00057"
   }
,
  {
      "is_managed" : "true",
      "guid" : "D5E8B245-CDEC-4B5A-9770-76E31BB9BD7E",
      "token" : "0x00000",
      "native_offset" : "0x0",
      "filename" : "MonoDevelop.MSBuildBuilder.exe",
      "sizeofimage" : "0x14000",
      "timestamp" : "0x88f6a782",
      "il_offset" : "0x0002a"
   }
,
  {
      "is_managed" : "false",
      "native_address" : "unregistered"
   }
,
  {
      "is_managed" : "true",
      "guid" : "7D0BC631-CADD-4A07-BF74-717847E90CFA",
      "token" : "0x00000",
      "native_offset" : "0x0",
      "filename" : "mscorlib.dll",
      "sizeofimage" : "0x472000",
      "timestamp" : "0xec216ac8",
      "il_offset" : "0x0000c"
   }
,
  {
      "is_managed" : "true",
      "guid" : "7D0BC631-CADD-4A07-BF74-717847E90CFA",
      "token" : "0x60048c4",
      "native_offset" : "0x0",
      "filename" : "mscorlib.dll",
      "sizeofimage" : "0x472000",
      "timestamp" : "0xec216ac8",
      "il_offset" : "0x00000"
   }
,
  {
      "is_managed" : "true",
      "guid" : "D5E8B245-CDEC-4B5A-9770-76E31BB9BD7E",
      "token" : "0x6000039",
      "native_offset" : "0x0",
      "filename" : "MonoDevelop.MSBuildBuilder.exe",
      "sizeofimage" : "0x14000",
      "timestamp" : "0x88f6a782",
      "il_offset" : "0x00019"
   }
,
  {
      "is_managed" : "true",
      "guid" : "D5E8B245-CDEC-4B5A-9770-76E31BB9BD7E",
      "token" : "0x6000166",
      "native_offset" : "0x0",
      "filename" : "MonoDevelop.MSBuildBuilder.exe",
      "sizeofimage" : "0x14000",
      "timestamp" : "0x88f6a782",
      "il_offset" : "0x00029"
   }
,
  {
      "is_managed" : "true",
      "guid" : "D5E8B245-CDEC-4B5A-9770-76E31BB9BD7E",
      "token" : "0x6000181",
      "native_offset" : "0x0",
      "filename" : "MonoDevelop.MSBuildBuilder.exe",
      "sizeofimage" : "0x14000",
      "timestamp" : "0x88f6a782",
      "il_offset" : "0x00001"
   }
,
  {
      "is_managed" : "true",
      "guid" : "7D0BC631-CADD-4A07-BF74-717847E90CFA",
      "token" : "0x6001ec3",
      "native_offset" : "0x0",
      "filename" : "mscorlib.dll",
      "sizeofimage" : "0x472000",
      "timestamp" : "0xec216ac8",
      "il_offset" : "0x00071"
   }
,
  {
      "is_managed" : "true",
      "guid" : "7D0BC631-CADD-4A07-BF74-717847E90CFA",
      "token" : "0x6001ec1",
      "native_offset" : "0x0",
      "filename" : "mscorlib.dll",
      "sizeofimage" : "0x472000",
      "timestamp" : "0xec216ac8",
      "il_offset" : "0x00000"
   }
,
  {
      "is_managed" : "true",
      "guid" : "7D0BC631-CADD-4A07-BF74-717847E90CFA",
      "token" : "0x00000",
      "native_offset" : "0x0",
      "filename" : "mscorlib.dll",
      "sizeofimage" : "0x472000",
      "timestamp" : "0xec216ac8",
      "il_offset" : "0x0002a"
   }

  ],
  "unmanaged_frames" : [
 {
    "is_managed" : "false",
    "native_address" : "0x109a82156",
    "native_offset" : "0x00000"
  }
,
 {
    "is_managed" : "false",
    "native_address" : "0x109c28775",
    "native_offset" : "0x00000"
  }
,
 {
    "is_managed" : "false",
    "native_address" : "0x109c28dfa",
    "native_offset" : "0x00000"
  }
,
 {
    "is_managed" : "false",
    "native_address" : "0x109aedf46",
    "native_offset" : "0x00000"
  }
,
 {
    "is_managed" : "false",
    "native_address" : "0x109a86c65",
    "native_offset" : "0x00000"
  }
,
 {
    "is_managed" : "false",
    "native_address" : "0x109aed2db",
    "native_offset" : "0x00000"
  }
,
 {
    "is_managed" : "false",
    "native_address" : "0x7fff6c1c95fd",
    "native_offset" : "0x00000"
  }
,
 {
    "is_managed" : "false",
    "native_address" : "unregistered"
  }
,
 {
    "is_managed" : "false",
    "native_address" : "0x7fff6c09f808",
    "native_offset" : "0x00000"
  }
,
 {
    "is_managed" : "false",
    "native_address" : "0x109cf7cb7",
    "native_offset" : "0x00000"
  }
,
 {
    "is_managed" : "false",
    "native_address" : "0x109cd8b2f",
    "native_offset" : "0x00000"
  }
,
 {
    "is_managed" : "false",
    "native_address" : "0x109cf803e",
    "native_offset" : "0x00000"
  }
,
 {
    "is_managed" : "false",
    "native_address" : "0x109cf81bf",
    "native_offset" : "0x00000"
  }
,
 {
    "is_managed" : "false",
    "native_address" : "0x109b92e76",
    "native_offset" : "0x00000"
  }
,
 {
    "is_managed" : "false",
    "native_address" : "0x109b93478",
    "native_offset" : "0x00000"
  }
,
 {
    "is_managed" : "false",
    "native_address" : "0x109ce619f",
    "native_offset" : "0x00000"
  }
,
 {
    "is_managed" : "false",
    "native_address" : "0x109ce64b0",
    "native_offset" : "0x00000"
  }
,
 {
    "is_managed" : "false",
    "native_address" : "0x109b957ab",
    "native_offset" : "0x00000"
  }
,
 {
    "is_managed" : "false",
    "native_address" : "0x109bb8675",
    "native_offset" : "0x00000"
  }
,
 {
    "is_managed" : "true",
    "guid" : "7D0BC631-CADD-4A07-BF74-717847E90CFA",
    "token" : "0x00000",
    "native_offset" : "0x0",
    "filename" : "mscorlib.dll",
    "sizeofimage" : "0x472000",
    "timestamp" : "0xec216ac8",
    "il_offset" : "0x00000"
  }
,
 {
    "is_managed" : "true",
    "guid" : "D5E8B245-CDEC-4B5A-9770-76E31BB9BD7E",
    "token" : "0x6000083",
    "native_offset" : "0x0",
    "filename" : "MonoDevelop.MSBuildBuilder.exe",
    "sizeofimage" : "0x14000",
    "timestamp" : "0x88f6a782",
    "il_offset" : "0x00000"
  }
,
 {
    "is_managed" : "true",
    "guid" : "D5E8B245-CDEC-4B5A-9770-76E31BB9BD7E",
    "token" : "0x60000a1",
    "native_offset" : "0x0",
    "filename" : "MonoDevelop.MSBuildBuilder.exe",
    "sizeofimage" : "0x14000",
    "timestamp" : "0x88f6a782",
    "il_offset" : "0x00000"
  }
,
 {
    "is_managed" : "true",
    "guid" : "D5E8B245-CDEC-4B5A-9770-76E31BB9BD7E",
    "token" : "0x00000",
    "native_offset" : "0x0",
    "filename" : "MonoDevelop.MSBuildBuilder.exe",
    "sizeofimage" : "0x14000",
    "timestamp" : "0x88f6a782",
    "il_offset" : "0x00000"
  }
,
 {
    "is_managed" : "false",
    "native_address" : "0x1099e262d",
    "native_offset" : "0x00000"
  }
,
 {
    "is_managed" : "false",
    "native_address" : "0x109c01fa4",
    "native_offset" : "0x00000"
  }
,
 {
    "is_managed" : "false",
    "native_address" : "0x109c063a6",
    "native_offset" : "0x00000"
  }
,
 {
    "is_managed" : "false",
    "native_address" : "0x109b9d6f4",
    "native_offset" : "0x00000"
  }
,
 {
    "is_managed" : "true",
    "guid" : "7D0BC631-CADD-4A07-BF74-717847E90CFA",
    "token" : "0x00000",
    "native_offset" : "0x0",
    "filename" : "mscorlib.dll",
    "sizeofimage" : "0x472000",
    "timestamp" : "0xec216ac8",
    "il_offset" : "0x00000"
  }
,
 {
    "is_managed" : "true",
    "guid" : "7D0BC631-CADD-4A07-BF74-717847E90CFA",
    "token" : "0x60048c4",
    "native_offset" : "0x0",
    "filename" : "mscorlib.dll",
    "sizeofimage" : "0x472000",
    "timestamp" : "0xec216ac8",
    "il_offset" : "0x00000"
  }
,
 {
    "is_managed" : "true",
    "guid" : "D5E8B245-CDEC-4B5A-9770-76E31BB9BD7E",
    "token" : "0x6000181",
    "native_offset" : "0x0",
    "filename" : "MonoDevelop.MSBuildBuilder.exe",
    "sizeofimage" : "0x14000",
    "timestamp" : "0x88f6a782",
    "il_offset" : "0x00000"
  }
,
 {
    "is_managed" : "true",
    "guid" : "7D0BC631-CADD-4A07-BF74-717847E90CFA",
    "token" : "0x6001ec1",
    "native_offset" : "0x0",
    "filename" : "mscorlib.dll",
    "sizeofimage" : "0x472000",
    "timestamp" : "0xec216ac8",
    "il_offset" : "0x00000"
  }
,
 {
    "is_managed" : "true",
    "guid" : "(null)",
    "token" : "0x00000",
    "native_offset" : "0x0",
    "filename" : "(null)",
    "sizeofimage" : "0x0",
    "timestamp" : "0x0",
    "il_offset" : "0x00000"
  }
,
 {
    "is_managed" : "false",
    "native_address" : "0x1099e262d",
    "native_offset" : "0x00000"
  }
,
 {
    "is_managed" : "false",
    "native_address" : "0x109c01fa4",
    "native_offset" : "0x00000"
  }
,
 {
    "is_managed" : "false",
    "native_address" : "0x109c2bec0",
    "native_offset" : "0x00000"
  }
,
 {
    "is_managed" : "false",
    "native_address" : "0x109b5e28c",
    "native_offset" : "0x00000"
  }
,
 {
    "is_managed" : "false",
    "native_address" : "0x109c29373",
    "native_offset" : "0x00000"
  }
,
 {
    "is_managed" : "false",
    "native_address" : "0x7fff6c1d5109",
    "native_offset" : "0x00000"
  }
,
 {
    "is_managed" : "false",
    "native_address" : "0x7fff6c1d0b8b",
    "native_offset" : "0x00000"
  }

 ]
}
]
}